gitignore_generator/__init__.py
gitignore_generator/main.py
gitignore_generator-0.1.1.data/data/templates/javascript.txt
gitignore_generator-0.1.1.data/data/templates/python.txt
gitignore_generator-0.1.1.dist-info/METADATA
gitignore_generator-0.1.1.dist-info/WHEEL
gitignore_generator-0.1.1.dist-info/entry_points.txt
gitignore_generator-0.1.1.dist-info/top_level.txt
gitignore_generator-0.1.1.dist-info/RECORD
