Metadata-Version: 2.4
Name: gitignore-generator
Version: 0.1.1
Summary: A CLI tool to generate gitignore files for different languages
Home-page: https://github.com/iBz-04/Gen_ignore
Author: Ibrahim Rayamah
Author-email: issakaibrahimrayamah@gmail.com
Keywords: git,gitignore,cli
Classifier: Programming Language :: Python :: 3
Classifier: License :: OSI Approved :: MIT License
Classifier: Operating System :: OS Independent
Requires-Python: >=3.6
Dynamic: author
Dynamic: author-email
Dynamic: classifier
Dynamic: description
Dynamic: description-content-type
Dynamic: home-page
Dynamic: keywords
Dynamic: requires-python
Dynamic: summary
